elixir_training_mcp/QUERIES.md
elixir_training_mcp/__init__.py
elixir_training_mcp/data_models.py
elixir_training_mcp/data_store.py
elixir_training_mcp/mcp_server.py
elixir_training_mcp/models.py
elixir_training_mcp/services.py
elixir_training_mcp/tools.py
elixir_training_mcp/vectordb.py
elixir_training_mcp/data/gtn_harvest.ttl
elixir_training_mcp/data/tess_harvest.ttl
elixir_training_mcp/harvest/harvest_gtn.py
elixir_training_mcp/harvest/harvest_tess.py
elixir_training_mcp/indexes/__init__.py
elixir_training_mcp/indexes/date.py
elixir_training_mcp/indexes/keyword.py
elixir_training_mcp/indexes/location.py
elixir_training_mcp/indexes/provider.py
elixir_training_mcp/indexes/topic.py
elixir_training_mcp/indexes/utils.py
elixir_training_mcp/loader/__init__.py
elixir_training_mcp/loader/dedupe.py
elixir_training_mcp/loader/graph.py
elixir_training_mcp/loader/parser.py
elixir_training_mcp/loader/utils.py
elixir_training_mcp-0.0.3.dist-info/METADATA
elixir_training_mcp-0.0.3.dist-info/WHEEL
elixir_training_mcp-0.0.3.dist-info/entry_points.txt
elixir_training_mcp-0.0.3.dist-info/licenses/LICENSE
elixir_training_mcp-0.0.3.dist-info/RECORD
