Metadata-Version: 2.4
Name: elixir-training-mcp
Version: 0.0.3
Summary: A Model Context Protocol (MCP) server to access data about training materials.
Project-URL: Homepage, https://github.com/elixir-europe-training/ELIXIR-TrP-KG-training-metadata
Project-URL: Documentation, https://github.com/elixir-europe-training/ELIXIR-TrP-KG-training-metadata
Project-URL: History, https://github.com/elixir-europe-training/ELIXIR-TrP-KG-training-metadata/releases
Project-URL: Tracker, https://github.com/elixir-europe-training/ELIXIR-TrP-KG-training-metadata/issues
Project-URL: Source, https://github.com/elixir-europe-training/ELIXIR-TrP-KG-training-metadata
Author-email: Vincent Emonet <vincent.emonet@gmail.com>
Maintainer-email: Vincent Emonet <vincent.emonet@gmail.com>
License: MIT License
License-File: LICENSE
Keywords: Elixir,MCP,Search,Training
Classifier: License :: OSI Approved :: MIT License
Classifier: Operating System :: OS Independent
Classifier: Programming Language :: Python :: 3
Classifier: Programming Language :: Python :: 3.10
Classifier: Programming Language :: Python :: 3.11
Classifier: Programming Language :: Python :: 3.12
Classifier: Programming Language :: Python :: 3.13
Requires-Python: >=3.10
Requires-Dist: extruct>=0.16.0
Requires-Dist: httpx>=0.28.1
Requires-Dist: lxml>=5.0.0
Requires-Dist: mcp>=1.19.0
Requires-Dist: pydantic-settings>=2.11.0
Requires-Dist: pydantic>=2.12.0
Requires-Dist: pyld>=2.0.4
Requires-Dist: rdflib>=7.4.0
Requires-Dist: w3lib>=2.2.0
